dt_apriltags/__init__.py
dt_apriltags/apriltags.py
dt_apriltags/libapriltag.so
dt_apriltags-3.1.7.dist-info/DESCRIPTION.rst
dt_apriltags-3.1.7.dist-info/METADATA
dt_apriltags-3.1.7.dist-info/RECORD
dt_apriltags-3.1.7.dist-info/WHEEL
dt_apriltags-3.1.7.dist-info/metadata.json
dt_apriltags-3.1.7.dist-info/top_level.txt
