Metadata-Version: 2.0
Name: dt-apriltags
Version: 3.1.7
Summary: UNKNOWN
Home-page: https://github.com/duckietown/lib-dt-apriltags
Author: Aleksandar Petrov
Author-email: alpetrov@ethz.ch
License: UNKNOWN
Platform: UNKNOWN
Requires-Dist: numpy
